cordex/__init__.py
cordex/accessor.py
cordex/cf.py
cordex/cli.py
cordex/config.py
cordex/domain.py
cordex/esgf_access.py
cordex/transform.py
cordex/tutorial.py
cordex/utils.py
cordex/variable.py
cordex/cmor/__init__.py
cordex/cmor/cmor.py
cordex/cmor/config.py
cordex/cmor/utils.py
cordex/preprocessing/__init__.py
cordex/preprocessing/known_issues.py
cordex/preprocessing/preprocessing.py
cordex/regions/__init__.py
cordex/regions/_germany.py
cordex/regions/_prudence.py
cordex/regions/_regions.py
cordex/regions/_resources.py
cordex/tables/__init__.py
cordex/tables/_resources.py
py_cordex-0.10.2.dist-info/licenses/LICENSE
py_cordex-0.10.2.dist-info/METADATA
py_cordex-0.10.2.dist-info/WHEEL
py_cordex-0.10.2.dist-info/top_level.txt
py_cordex-0.10.2.dist-info/RECORD
