Metadata-Version: 2.4
Name: py-cordex
Version: 0.10.2
Summary: Creation of cordex grids and meta data
License: MIT License
Project-URL: homepage, https://py-cordex.readthedocs.io
Project-URL: documentation, https://py-cordex.readthedocs.io
Project-URL: repository, https://github.com/euro-cordex/py-cordex.git
Project-URL: changelog, https://py-cordex.readthedocs.io/en/latest/whats-new.html
Keywords: cordex,xarray,metadata,CF conventions
Classifier: Development Status :: 5 - Production/Stable
Classifier: License :: OSI Approved :: MIT License
Classifier: Natural Language :: English
Classifier: Operating System :: OS Independent
Classifier: Programming Language :: Python
Classifier: Programming Language :: Python :: 3.9
Classifier: Programming Language :: Python :: 3.10
Classifier: Programming Language :: Python :: 3.11
Classifier: Programming Language :: Python :: 3.12
Classifier: Programming Language :: Python :: 3.13
Requires-Python: >=3.9
License-File: LICENSE
Requires-Dist: xarray!=2023.9.0
Requires-Dist: cf-xarray>=0.8
Requires-Dist: pooch
Requires-Dist: pyproj>=3.3.0
Dynamic: license-file
